[
  {
    "id": 1779466024022,
    "title": "Series de Taylor (análisis complejo)",
    "body": "Acabo de publicar un repositorio en GitHub con el código de las visualizaciones que hice de series de Taylor para variable compleja usando técnicas de *domain coloring*. Las hice para para mostrarles a los chicos de Cálculo III (Cálculo complejo), así tenían una mejor idea de cómo convergen las aproximaciones en serie de potencias. Y la verdad es que me sirvió bastante a mí también. Igual hay que tener en cuenta que el dominio coloreado solo me habla del argumento y no del módulo.\n\nDejo la animación para $f(z) = \\frac{1}{1-z}$, con el desarrollo centrado en $z_0=0$, que se realiza usando la serie geométrica, converge para el disco $|z|<1$.\n\nEl link al repo es este: **https://github.com/vickyguar/Taylor**\n\nAh, y este es mi primer posteo a este blog :) no creo que sea constante con esto pero me divirtió programarlo jaja...",
    "date": "2026-05-22T16:07:04.022Z",
    "tags": [
      "matemática"
    ],
    "color": "yellow",
    "image": "fotos/1779466019956_geom.gif",
    "comments": [
      {
        "author": "Victoria",
        "body": "Ah, btw:\n\n**Teorema.** Supongamos que una función $f$ es analítica en todo un disco $|z-z_0|<R$, centrado en $z_0$ con radio $R$. Entonces $f(z)$ tiene la representación en serie de potencias\n\n$$\nf(z) = \\sum_{n=0}^{\\infty} a_n (z-z_0)^n, \\quad |z-z_0| \\lt R, \\qquad (1)\n$$\n\ndonde\n\n$$\na_n = \\frac{f^{(n)}(z_0)}{n!}, \\quad n=0,1,2,\\cdots \\qquad (2)\n$$\n\nEs decir, la serie $(1)$ converge a $f(z)$ cuando $z$ se encuentra en el disco abierto indicado.",
        "date": "2026-05-22T16:09:50.748Z"
      }
    ]
  }
]